idu/__init__.py
idu/__main__.py
idu/report.py
idu/utils.py
idu_network_monitor-0.1.0.dist-info/licenses/LICENSE
idu_network_monitor-0.1.0.dist-info/METADATA
idu_network_monitor-0.1.0.dist-info/WHEEL
idu_network_monitor-0.1.0.dist-info/entry_points.txt
idu_network_monitor-0.1.0.dist-info/top_level.txt
idu_network_monitor-0.1.0.dist-info/RECORD
