Metadata-Version: 2.4
Name: idu-network-monitor
Version: 0.1.0
Summary: A network data usage monitor that generates beautiful HTML reports with interactive charts
Author-email: IDU Development Team <idu@example.com>
License-Expression: MIT
Project-URL: Homepage, https://github.com/yourusername/idu
Project-URL: Documentation, https://github.com/yourusername/idu#readme
Project-URL: Repository, https://github.com/yourusername/idu.git
Project-URL: Issues, https://github.com/yourusername/idu/issues
Keywords: network,monitor,data usage,bandwidth,internet,traffic,analytics,report,visualization
Classifier: Development Status :: 4 - Beta
Classifier: Environment :: Console
Classifier: Intended Audience :: End Users/Desktop
Classifier: Intended Audience :: System Administrators
Classifier: Operating System :: OS Independent
Classifier: Operating System :: Microsoft :: Windows
Classifier: Operating System :: POSIX :: Linux
Classifier: Operating System :: MacOS :: MacOS X
Classifier: Programming Language :: Python :: 3
Classifier: Programming Language :: Python :: 3.8
Classifier: Programming Language :: Python :: 3.9
Classifier: Programming Language :: Python :: 3.10
Classifier: Programming Language :: Python :: 3.11
Classifier: Programming Language :: Python :: 3.12
Classifier: Topic :: System :: Monitoring
Classifier: Topic :: System :: Networking :: Monitoring
Classifier: Topic :: Utilities
Requires-Python: >=3.8
License-File: LICENSE
Requires-Dist: psutil>=5.9.0
Provides-Extra: notebook
Requires-Dist: pandas>=1.3.0; extra == "notebook"
Requires-Dist: plotly>=5.0.0; extra == "notebook"
Requires-Dist: jupyter>=1.0.0; extra == "notebook"
Provides-Extra: dev
Requires-Dist: pytest>=7.0.0; extra == "dev"
Requires-Dist: pytest-cov>=4.0.0; extra == "dev"
Requires-Dist: black>=23.0.0; extra == "dev"
Requires-Dist: flake8>=6.0.0; extra == "dev"
Requires-Dist: mypy>=1.0.0; extra == "dev"
Dynamic: license-file
